fpga/radiant_project/lab02/source/impl_1/seven_segment.sv
/***
	Carried over from Lab 1.
	
	The seven_segment module used in lab 1 of MicroP's.
	
	Uses combinational logic to control a 7-segment LED matrix
	
	@input: s   :: a vector of what switches are turned on on the board
	@output seg :: a vector of seven bits that light up according to the order of on-board DIP switches
					Ranges from 0-9, A-F 
					(mapping wise: maps 1, 2, 3, 4, 5, 6, 7, 8, 9, 0, A, b, C, d, E, F to corresponding switch orders)
	
	author: zoe worrall
	version: 9/1/2024
	contact: zworrall@g.hmc.edu
*/

// For future improvement: typedef enum logic[6:0] { num1=7'b111_1001, num2=7'b010_0100, num3=7'b011_0000, num4=7'b001_1001, num5=7'b001_0010, num6=7'b000_0010, num7=7'b111_1000, num8=7'b000_0000, num9=7'b001_0000, num0=7'b100_0000, numA=7'b000_1000, numB=7'b000_0011, numC=7'b100_0110, numD=7'b010_0001, numE=7'b000_0110, numF=7'b000_1110} num_type;

module seven_segment(
	 input   logic [3:0] s,
	 output  logic [6:0] seg);
	
	// num_type nums;
	// makes a logic table that is called whenever a rule is made, which sets all relevant segments
		// although it is possible to simplify the boolean equations for the segments, it was simpler
		// for me to make it using a case statement
	always_comb begin
		// seg = num_type'(s);
		
		case (s)
			0: 		 seg = 7'b100_0000;		 
			1:		 seg = 7'b111_1001;
			2: 		 seg = 7'b010_0100; 
			3: 		 seg = 7'b011_0000;
			
			4: 		 seg = 7'b001_1001;
			5: 		 seg = 7'b001_0010;
			6: 		 seg = 7'b000_0010;
			7: 		 seg = 7'b111_1000;
			
			8: 		 seg = 7'b000_0000;
			9: 		 seg = 7'b001_0000;
			10:		 seg = 7'b000_1000;
			11:		 seg = 7'b000_0011;
			
			12:		 seg = 7'b100_0110;
			13:		 seg = 7'b010_0001;
			14:		 seg = 7'b000_0110;
			15: 	 seg = 7'b000_1110;
			default:  seg = 7'bxxx_xxxx;
		endcase
		
	end
	
endmodule

fpga/radiant_project/lab02/source/impl_1/dual_seven_seg.sv
/***
	Generates and multiplexes a seven-segment display using one seven segment display module
	
	author: zoe worrall
	version: 09/06/2024
	contact: zworrall@g.hmc.edu
*/

module dual_seven_seg(
     input   logic state,  // statetype variable letting us know whether display 0 or display 1 is on
	 input	logic  [3:0] s1, s2,
	 output  logic [6:0] seg,  // GPIO power for seg1 and seg 2
	 output logic 		anode_display1, anode_display2	// if we are powering first (0) or second (1) segment
);	  
	  logic [3:0] s;

	  // the generated seven segmenet display. Displays according to the current switch.
	  seven_segment segment(s, seg);
	  
	  // controls which switch will be used by the seven segment display
	  always_comb begin
		  if (state == S1) begin // display1 on: this one depends on s1
				s = s1;
				anode_display1 = 0; // allow current flow
				anode_display2 = 1; // common anode of 2 is off
		  end else if (state == S0) begin // depends on input of s2
				s = s2;
				anode_display1 = 1;
				anode_display2 = 0;  
		  end else begin // This means that the finite state machine is broken
				s = 0;
				anode_display1 = 1;
				anode_display2 = 1;
		end
	  end 
  
endmodule

fpga/radiant_project/lab02/source/impl_1/dual_seven_seg_tb.sv
/***
  A Testbench meant to test all possible cases of switch pins used within the lab.
	Based off of the fulladder testbench inside of the MicroP's page.

  Calls on a text file "lab02_testvectors.tv", however due to odd pathing the full
	address of the file to computer needed to be written. For future users, it
	will be necessary to replace this current pathing with their own to ensure
	the right connection and no errors being thrown during Simulation.

  @author: zoe worrall
	   zworrall@g.hmc.edu
  @version: 09/05/2024
  
*/
`timescale 1ns/1ns
`default_nettype none
`define N_TV 512

module dual_seven_seg_tb();

 // Set up test signals
 logic clk, reset; 					// clk is necessary in all test benches
 logic 		 state;
 logic [3:0] switch1, switch2;		// the switches. On the board, each bit represents a switch
 logic [6:0] segment, seg_expected, seg2_expected; // the segments of the matrix. 
 logic anode1, anode1_expected, anode2, anode2_expected;				// will not be checked because this is clock dependent (send help plz)
 logic [511:0] vectornum, errors;     // the way that we iterate through the table of test vectors
 logic [19:0] testvectors [10000:0]; // Vectors of format s1[3:0]_s2[3:0]_display1_seg[6:0]_anode1_anode2

/***
			logic state,  // statetype variable letting us know whether display 0 or display 1 is on
	 input	logic  [3:0] s1, s2,
	 output  logic [6:0] seg,  // GPIO power for seg1 and seg 2
	 output logic 		anode_display1, anode_display2 */

 // Instatiation of lab 1's top module
 dual_seven_seg dut (
	.state (state), 
	.s1 (switch1),
	.s2 (switch2),
	.seg (segment),
	.anode_display1 (anode1),
	.anode_display2 (anode2)
   );
   

 // Generate clock signal with a period of 10 timesteps (5 up, 5 down)
 always
   begin
     clk = 1; #5;
     clk = 0; #5;
   end
  
 // At the start of the simulation:
 //  - Load the testvectors
 //  - Pulse the reset line
 initial
   begin
     $readmemb("C:/Users/zoeworrall/Desktop/projects_LRS/lab02/source/impl_1/dualseg_lab02_testvectors.tv", testvectors, 0, `N_TV - 1);
     vectornum = 0; errors = 0;
     reset = 1; #27; reset = 0;
   end

  // Apply test vector on the rising edge of clk
 always @(posedge clk)
   begin
       #1; {switch1, switch2, state, seg_expected, anode1_expected, anode2_expected} = testvectors[vectornum];
   end
  initial

 begin
   // Create dumpfile for signals; this will help with debugging in later labs
   $dumpfile("dual_seven_seg_tb.vcd");
   $dumpvars(0, dual_seven_seg_tb);
 end

  // Check results on the falling edge of clk
 always @(negedge clk)
   begin
     if (~reset) // skip during reset
       begin
         if (segment != seg_expected || anode1 != anode1_expected || anode2 != anode2_expected)
           begin
             $display("Error: inputs: switch1=%b, switch2=%b", switch1, switch2);
             $display(" outputs: seg=%b (%b expected), anode1=%b (%b expected), anode2=%b (%b expected)", segment, seg_expected, anode1, anode1_expected, anode2, anode2_expected);
             errors = errors + 1;
           end

       // iterate through each vector in the testbench
       vectornum = vectornum + 1;
      
       if (testvectors[vectornum] === 14'bx)
         begin
           $display("%d tests completed with %d errors.", vectornum, errors);
	   // $finish; commented out to see the waveforms
         end
     end
   end
endmodule

fpga/radiant_project/lab02/source/impl_1/dual_seven_seg_tb.vcd
$date
	Thu Sep  5 18:41:12 2024
$end
$version
	Questa Lattice OEM Edition 2024.2
$end
$timescale
	1ns
$end

$scope module dual_seven_seg_tb $end
$var reg 1 ! clk $end
$var reg 1 " reset $end
$var reg 1 # state $end
$var reg 4 $ switch1 [3:0] $end
$var reg 4 % switch2 [3:0] $end
$var reg 7 & segment [6:0] $end
$var reg 7 ' seg_expected [6:0] $end
$var reg 7 ( seg2_expected [6:0] $end
$var reg 1 ) anode1 $end
$var reg 1 * anode1_expected $end
$var reg 1 + anode2 $end
$var reg 1 , anode2_expected $end
$var reg 512 - vectornum [511:0] $end
$var reg 512 . errors [511:0] $end

$scope module dut $end
$var wire 1 / state $end
$var wire 1 0 s1 [3] $end
$var wire 1 1 s1 [2] $end
$var wire 1 2 s1 [1] $end
$var wire 1 3 s1 [0] $end
$var wire 1 4 s2 [3] $end
$var wire 1 5 s2 [2] $end
$var wire 1 6 s2 [1] $end
$var wire 1 7 s2 [0] $end
$var reg 7 8 seg [6:0] $end
$var reg 1 9 anode_display1 $end
$var reg 1 : anode_display2 $end
$var reg 4 ; s [3:0] $end

$scope module segment $end
$var wire 1 < s [3] $end
$var wire 1 = s [2] $end
$var wire 1 > s [1] $end
$var wire 1 ? s [0] $end
$var reg 7 @ seg [6:0] $end
$upscope $end
$upscope $end
$upscope $end
$enddefinitions $end
#0
$dumpvars
1!
1"
x#
bx $
bx %
b1000000 &
bx '
bx (
1)
x*
1+
x,
b0 -
b0 .
b1000000 8
19
1:
b0 ;
b1000000 @
x7
x6
x5
x4
x3
x2
x1
x0
x/
0?
0>
0=
0<
$end
#1
1,
0*
b1000000 '
1#
b0 %
b0 $
1/
03
02
01
00
07
06
05
04
09
0)
#5
0!
#10
1!
#15
0!
#20
1!
#25
0!
#27
0"
#30
1!
#35
0!
b1 -
#40
1!
#41
b1 %
17
#45
0!
b10 -
#50
1!
#51
b10 %
07
16
#55
0!
b11 -
#60
1!
#61
b11 %
17
#65
0!
b100 -
#70
1!
#71
b100 %
07
06
15
#75
0!
b101 -
#80
1!
#81
b101 %
17
#85
0!
b110 -
#90
1!
#91
b110 %
07
16
#95
0!
b111 -
#100
1!
#101
b111 %
17
#105
0!
b1000 -
#110
1!
#111
b1000 %
07
06
05
14
#115
0!
b1001 -
#120
1!
#121
b1001 %
17
#125
0!
b1010 -
#130
1!
#131
b1010 %
07
16
#135
0!
b1011 -
#140
1!
#141
b1011 %
17
#145
0!
b1100 -
#150
1!
#151
b1100 %
07
06
15
#155
0!
b1101 -
#160
1!
#161
b1101 %
17
#165
0!
b1110 -
#170
1!
#171
b1110 %
07
16
#175
0!
b1111 -
#180
1!
#181
b1111 %
17
#185
0!
b10000 -
#190
1!
#191
b1111001 '
b0 %
b1 $
13
07
06
05
04
b1 ;
1?
b1111001 @
b1111001 8
b1111001 &
#195
0!
b10001 -
#200
1!
#201
b1 %
17
#205
0!
b10010 -
#210
1!
#211
b10 %
07
16
#215
0!
b10011 -
#220
1!
#221
b11 %
17
#225
0!
b10100 -
#230
1!
#231
b100 %
07
06
15
#235
0!
b10101 -
#240
1!
#241
b101 %
17
#245
0!
b10110 -
#250
1!
#251
b110 %
07
16
#255
0!
b10111 -
#260
1!
#261
b111 %
17
#265
0!
b11000 -
#270
1!
#271
b1000 %
07
06
05
14
#275
0!
b11001 -
#280
1!
#281
b1001 %
17
#285
0!
b11010 -
#290
1!
#291
b1010 %
07
16
#295
0!
b11011 -
#300
1!
#301
b1011 %
17
#305
0!
b11100 -
#310
1!
#311
b1100 %
07
06
15
#315
0!
b11101 -
#320
1!
#321
b1101 %
17
#325
0!
b11110 -
#330
1!
#331
b1110 %
07
16
#335
0!
b11111 -
#340
1!
#341
b1111 %
17
#345
0!
b100000 -
#350
1!
#351
b100100 '
b0 %
b10 $
03
12
07
06
05
04
b10 ;
0?
1>
b100100 @
b100100 8
b100100 &
#355
0!
b100001 -
#360
1!
#361
b1 %
17
#365
0!
b100010 -
#370
1!
#371
b10 %
07
16
#375
0!
b100011 -
#380
1!
#381
b11 %
17
#385
0!
b100100 -
#390
1!
#391
b100 %
07
06
15
#395
0!
b100101 -
#400
1!
#401
b101 %
17
#405
0!
b100110 -
#410
1!
#411
b110 %
07
16
#415
0!
b100111 -
#420
1!
#421
b111 %
17
#425
0!
b101000 -
#430
1!
#431
b1000 %
07
06
05
14
#435
0!
b101001 -
#440
1!
#441
b1001 %
17
#445
0!
b101010 -
#450
1!
#451
b1010 %
07
16
#455
0!
b101011 -
#460
1!
#461
b1011 %
17
#465
0!
b101100 -
#470
1!
#471
b1100 %
07
06
15
#475
0!
b101101 -
#480
1!
#481
b1101 %
17
#485
0!
b101110 -
#490
1!
#491
b1110 %
07
16
#495
0!
b101111 -
#500
1!
#501
b1111 %
17
#505
0!
b110000 -
#510
1!
#511
b110000 '
b0 %
b11 $
13
07
06
05
04
b11 ;
1?
b110000 @
b110000 8
b110000 &
#515
0!
b110001 -
#520
1!
#521
b1 %
17
#525
0!
b110010 -
#530
1!
#531
b10 %
07
16
#535
0!
b110011 -
#540
1!
#541
b11 %
17
#545
0!
b110100 -
#550
1!
#551
b100 %
07
06
15
#555
0!
b110101 -
#560
1!
#561
b101 %
17
#565
0!
b110110 -
#570
1!
#571
b110 %
07
16
#575
0!
b110111 -
#580
1!
#581
b111 %
17
#585
0!
b111000 -
#590
1!
#591
b1000 %
07
06
05
14
#595
0!
b111001 -
#600
1!
#601
b1001 %
17
#605
0!
b111010 -
#610
1!
#611
b1010 %
07
16
#615
0!
b111011 -
#620
1!
#621
b1011 %
17
#625
0!
b111100 -
#630
1!
#631
b1100 %
07
06
15
#635
0!
b111101 -
#640
1!
#641
b1101 %
17
#645
0!
b111110 -
#650
1!
#651
b1110 %
07
16
#655
0!
b111111 -
#660
1!
#661
b1111 %
17
#665
0!
b1000000 -
#670
1!
#671
b11001 '
b0 %
b100 $
03
02
11
07
06
05
04
b100 ;
0?
0>
1=
b11001 @
b11001 8
b11001 &
#675
0!
b1000001 -
#680
1!
#681
b1 %
17
#685
0!
b1000010 -
#690
1!
#691
b10 %
07
16
#695
0!
b1000011 -
#700
1!
#701
b11 %
17
#705
0!
b1000100 -
#710
1!
#711
b100 %
07
06
15
#715
0!
b1000101 -
#720
1!
#721
b101 %
17
#725
0!
b1000110 -
#730
1!
#731
b110 %
07
16
#735
0!
b1000111 -
#740
1!
#741
b111 %
17
#745
0!
b1001000 -
#750
1!
#751
b1000 %
07
06
05
14
#755
0!
b1001001 -
#760
1!
#761
b1001 %
17
#765
0!
b1001010 -
#770
1!
#771
b1010 %
07
16
#775
0!
b1001011 -
#780
1!
#781
b1011 %
17
#785
0!
b1001100 -
#790
1!
#791
b1100 %
07
06
15
#795
0!
b1001101 -
#800
1!
#801
b1101 %
17
#805
0!
b1001110 -
#810
1!
#811
b1110 %
07
16
#815
0!
b1001111 -
#820
1!
#821
b1111 %
17
#825
0!
b1010000 -
#830
1!
#831
b10010 '
b0 %
b101 $
13
07
06
05
04
b101 ;
1?
b10010 @
b10010 8
b10010 &
#835
0!
b1010001 -
#840
1!
#841
b1 %
17
#845
0!
b1010010 -
#850
1!
#851
b10 %
07
16
#855
0!
b1010011 -
#860
1!
#861
b11 %
17
#865
0!
b1010100 -
#870
1!
#871
b100 %
07
06
15
#875
0!
b1010101 -
#880
1!
#881
b101 %
17
#885
0!
b1010110 -
#890
1!
#891
b110 %
07
16
#895
0!
b1010111 -
#900
1!
#901
b111 %
17
#905
0!
b1011000 -
#910
1!
#911
b1000 %
07
06
05
14
#915
0!
b1011001 -
#920
1!
#921
b1001 %
17
#925
0!
b1011010 -
#930
1!
#931
b1010 %
07
16
#935
0!
b1011011 -
#940
1!
#941
b1011 %
17
#945
0!
b1011100 -
#950
1!
#951
b1100 %
07
06
15
#955
0!
b1011101 -
#960
1!
#961
b1101 %
17
#965
0!
b1011110 -
#970
1!
#971
b1110 %
07
16
#975
0!
b1011111 -
#980
1!
#981
b1111 %
17
#985
0!
b1100000 -
#990
1!
#991
b10 '
b0 %
b110 $
03
12
07
06
05
04
b110 ;
0?
1>
b10 @
b10 8
b10 &
#995
0!
b1100001 -
#1000
1!
#1001
b1 %
17
#1005
0!
b1100010 -
#1010
1!
#1011
b10 %
07
16
#1015
0!
b1100011 -
#1020
1!
#1021
b11 %
17
#1025
0!
b1100100 -
#1030
1!
#1031
b100 %
07
06
15
#1035
0!
b1100101 -
#1040
1!
#1041
b101 %
17
#1045
0!
b1100110 -
#1050
1!
#1051
b110 %
07
16
#1055
0!
b1100111 -
#1060
1!
#1061
b111 %
17
#1065
0!
b1101000 -
#1070
1!
#1071
b1000 %
07
06
05
14
#1075
0!
b1101001 -
#1080
1!
#1081
b1001 %
17
#1085
0!
b1101010 -
#1090
1!
#1091
b1010 %
07
16
#1095
0!
b1101011 -
#1100
1!
#1101
b1011 %
17
#1105
0!
b1101100 -
#1110
1!
#1111
b1100 %
07
06
15
#1115
0!
b1101101 -
#1120
1!
#1121
b1101 %
17
#1125
0!
b1101110 -
#1130
1!
#1131
b1110 %
07
16
#1135
0!
b1101111 -
#1140
1!
#1141
b1111 %
17
#1145
0!
b1110000 -
#1150
1!
#1151
b1111000 '
b0 %
b111 $
13
07
06
05
04
b111 ;
1?
b1111000 @
b1111000 8
b1111000 &
#1155
0!
b1110001 -
#1160
1!
#1161
b1 %
17
#1165
0!
b1110010 -
#1170
1!
#1171
b10 %
07
16
#1175
0!
b1110011 -
#1180
1!
#1181
b11 %
17
#1185
0!
b1110100 -
#1190
1!
#1191
b100 %
07
06
15
#1195
0!
b1110101 -
#1200
1!
#1201
b101 %
17
#1205
0!
b1110110 -
#1210
1!
#1211
b110 %
07
16
#1215
0!
b1110111 -
#1220
1!
#1221
b111 %
17
#1225
0!
b1111000 -
#1230
1!
#1231
b1000 %
07
06
05
14
#1235
0!
b1111001 -
#1240
1!
#1241
b1001 %
17
#1245
0!
b1111010 -
#1250
1!
#1251
b1010 %
07
16
#1255
0!
b1111011 -
#1260
1!
#1261
b1011 %
17
#1265
0!
b1111100 -
#1270
1!
#1271
b1100 %
07
06
15
#1275
0!
b1111101 -
#1280
1!
#1281
b1101 %
17
#1285
0!
b1111110 -
#1290
1!
#1291
b1110 %
07
16
#1295
0!
b1111111 -
#1300
1!
#1301
b1111 %
17
#1305
0!
b10000000 -
#1310
1!
#1311
b0 '
b0 %
b1000 $
03
02
01
10
07
06
05
04
b1000 ;
0?
0>
0=
1<
b0 @
b0 8
b0 &
#1315
0!
b10000001 -
#1320
1!
#1321
b1 %
17
#1325
0!
b10000010 -
#1330
1!
#1331
b10 %
07
16
#1335
0!
b10000011 -
#1340
1!
#1341
b11 %
17
#1345
0!
b10000100 -
#1350
1!
#1351
b100 %
07
06
15
#1355
0!
b10000101 -
#1360
1!
#1361
b101 %
17
#1365
0!
b10000110 -
#1370
1!
#1371
b110 %
07
16
#1375
0!
b10000111 -
#1380
1!
#1381
b111 %
17
#1385
0!
b10001000 -
#1390
1!
#1391
b1000 %
07
06
05
14
#1395
0!
b10001001 -
#1400
1!
#1401
b1001 %
17
#1405
0!
b10001010 -
#1410
1!
#1411
b1010 %
07
16
#1415
0!
b10001011 -
#1420
1!
#1421
b1011 %
17
#1425
0!
b10001100 -
#1430
1!
#1431
b1100 %
07
06
15
#1435
0!
b10001101 -
#1440
1!
#1441
b1101 %
17
#1445
0!
b10001110 -
#1450
1!
#1451
b1110 %
07
16
#1455
0!
b10001111 -
#1460
1!
#1461
b1111 %
17
#1465
0!
b10010000 -
#1470
1!
#1471
b10000 '
b0 %
b1001 $
13
07
06
05
04
b1001 ;
1?
b10000 @
b10000 8
b10000 &
#1475
0!
b10010001 -
#1480
1!
#1481
b1 %
17
#1485
0!
b10010010 -
#1490
1!
#1491
b10 %
07
16
#1495
0!
b10010011 -
#1500
1!
#1501
b11 %
17
#1505
0!
b10010100 -
#1510
1!
#1511
b100 %
07
06
15
#1515
0!
b10010101 -
#1520
1!
#1521
b101 %
17
#1525
0!
b10010110 -
#1530
1!
#1531
b110 %
07
16
#1535
0!
b10010111 -
#1540
1!
#1541
b111 %
17
#1545
0!
b10011000 -
#1550
1!
#1551
b1000 %
07
06
05
14
#1555
0!
b10011001 -
#1560
1!
#1561
b1001 %
17
#1565
0!
b10011010 -
#1570
1!
#1571
b1010 %
07
16
#1575
0!
b10011011 -
#1580
1!
#1581
b1011 %
17
#1585
0!
b10011100 -
#1590
1!
#1591
b1100 %
07
06
15
#1595
0!
b10011101 -
#1600
1!
#1601
b1101 %
17
#1605
0!
b10011110 -
#1610
1!
#1611
b1110 %
07
16
#1615
0!
b10011111 -
#1620
1!
#1621
b1111 %
17
#1625
0!
b10100000 -
#1630
1!
#1631
b1000 '
b0 %
b1010 $
03
12
07
06
05
04
b1010 ;
0?
1>
b1000 @
b1000 8
b1000 &
#1635
0!
b10100001 -
#1640
1!
#1641
b1 %
17
#1645
0!
b10100010 -
#1650
1!
#1651
b10 %
07
16
#1655
0!
b10100011 -
#1660
1!
#1661
b11 %
17
#1665
0!
b10100100 -
#1670
1!
#1671
b100 %
07
06
15
#1675
0!
b10100101 -
#1680
1!
#1681
b101 %
17
#1685
0!
b10100110 -
#1690
1!
#1691
b110 %
07
16
#1695
0!
b10100111 -
#1700
1!
#1701
b111 %
17
#1705
0!
b10101000 -
#1710
1!
#1711
b1000 %
07
06
05
14
#1715
0!
b10101001 -
#1720
1!
#1721
b1001 %
17
#1725
0!
b10101010 -
#1730
1!
#1731
b1010 %
07
16
#1735
0!
b10101011 -
#1740
1!
#1741
b1011 %
17
#1745
0!
b10101100 -
#1750
1!
#1751
b1100 %
07
06
15
#1755
0!
b10101101 -
#1760
1!
#1761
b1101 %
17
#1765
0!
b10101110 -
#1770
1!
#1771
b1110 %
07
16
#1775
0!
b10101111 -
#1780
1!
#1781
b1111 %
17
#1785
0!
b10110000 -
#1790
1!
#1791
b11 '
b0 %
b1011 $
13
07
06
05
04
b1011 ;
1?
b11 @
b11 8
b11 &
#1795
0!
b10110001 -
#1800
1!
#1801
b1 %
17
#1805
0!
b10110010 -
#1810
1!
#1811
b10 %
07
16
#1815
0!
b10110011 -
#1820
1!
#1821
b11 %
17
#1825
0!
b10110100 -
#1830
1!
#1831
b100 %
07
06
15
#1835
0!
b10110101 -
#1840
1!
#1841
b101 %
17
#1845
0!
b10110110 -
#1850
1!
#1851
b110 %
07
16
#1855
0!
b10110111 -
#1860
1!
#1861
b111 %
17
#1865
0!
b10111000 -
#1870
1!
#1871
b1000 %
07
06
05
14
#1875
0!
b10111001 -
#1880
1!
#1881
b1001 %
17
#1885
0!
b10111010 -
#1890
1!
#1891
b1010 %
07
16
#1895
0!
b10111011 -
#1900
1!
#1901
b1011 %
17
#1905
0!
b10111100 -
#1910
1!
#1911
b1100 %
07
06
15
#1915
0!
b10111101 -
#1920
1!
#1921
b1101 %
17
#1925
0!
b10111110 -
#1930
1!
#1931
b1110 %
07
16
#1935
0!
b10111111 -
#1940
1!
#1941
b1111 %
17
#1945
0!
b11000000 -
#1950
1!
#1951
b1000110 '
b0 %
b1100 $
03
02
11
07
06
05
04
b1100 ;
0?
0>
1=
b1000110 @
b1000110 8
b1000110 &
#1955
0!
b11000001 -
#1960
1!
#1961
b1 %
17
#1965
0!
b11000010 -
#1970
1!
#1971
b10 %
07
16
#1975
0!
b11000011 -
#1980
1!
#1981
b11 %
17
#1985
0!
b11000100 -
#1990
1!
#1991
b100 %
07
06
15
#1995
0!
b11000101 -
#2000
1!
#2001
b101 %
17
#2005
0!
b11000110 -
#2010
1!
#2011
b110 %
07
16
#2015
0!
b11000111 -
#2020
1!
#2021
b111 %
17
#2025
0!
b11001000 -
#2030
1!
#2031
b1000 %
07
06
05
14
#2035
0!
b11001001 -
#2040
1!
#2041
b1001 %
17
#2045
0!
b11001010 -
#2050
1!
#2051
b1010 %
07
16
#2055
0!
b11001011 -
#2060
1!
#2061
b1011 %
17
#2065
0!
b11001100 -
#2070
1!
#2071
b1100 %
07
06
15
#2075
0!
b11001101 -
#2080
1!
#2081
b1101 %
17
#2085
0!
b11001110 -
#2090
1!
#2091
b1110 %
07
16
#2095
0!
b11001111 -
#2100
1!
#2101
b1111 %
17
#2105
0!
b11010000 -
#2110
1!
#2111
b100001 '
b0 %
b1101 $
13
07
06
05
04
b1101 ;
1?
b100001 @
b100001 8
b100001 &
#2115
0!
b11010001 -
#2120
1!
#2121
b1 %
17
#2125
0!
b11010010 -
#2130
1!
#2131
b10 %
07
16
#2135
0!
b11010011 -
#2140
1!
#2141
b11 %
17
#2145
0!
b11010100 -
#2150
1!
#2151
b100 %
07
06
15
#2155
0!
b11010101 -
#2160
1!
#2161
b101 %
17
#2165
0!
b11010110 -
#2170
1!
#2171
b110 %
07
16
#2175
0!
b11010111 -
#2180
1!
#2181
b111 %
17
#2185
0!
b11011000 -
#2190
1!
#2191
b1000 %
07
06
05
14
#2195
0!
b11011001 -
#2200
1!
#2201
b1001 %
17
#2205
0!
b11011010 -
#2210
1!
#2211
b1010 %
07
16
#2215
0!
b11011011 -
#2220
1!
#2221
b1011 %
17
#2225
0!
b11011100 -
#2230
1!
#2231
b1100 %
07
06
15
#2235
0!
b11011101 -
#2240
1!
#2241
b1101 %
17
#2245
0!
b11011110 -
#2250
1!
#2251
b1110 %
07
16
#2255
0!
b11011111 -
#2260
1!
#2261
b1111 %
17
#2265
0!
b11100000 -
#2270
1!
#2271
b110 '
b0 %
b1110 $
03
12
07
06
05
04
b1110 ;
0?
1>
b110 @
b110 8
b110 &
#2275
0!
b11100001 -
#2280
1!
#2281
b1 %
17
#2285
0!
b11100010 -
#2290
1!
#2291
b10 %
07
16
#2295
0!
b11100011 -
#2300
1!
#2301
b11 %
17
#2305
0!
b11100100 -
#2310
1!
#2311
b100 %
07
06
15
#2315
0!
b11100101 -
#2320
1!
#2321
b101 %
17
#2325
0!
b11100110 -
#2330
1!
#2331
b110 %
07
16
#2335
0!
b11100111 -
#2340
1!
#2341
b111 %
17
#2345
0!
b11101000 -
#2350
1!
#2351
b1000 %
07
06
05
14
#2355
0!
b11101001 -
#2360
1!
#2361
b1001 %
17
#2365
0!
b11101010 -
#2370
1!
#2371
b1010 %
07
16
#2375
0!
b11101011 -
#2380
1!
#2381
b1011 %
17
#2385
0!
b11101100 -
#2390
1!
#2391
b1100 %
07
06
15
#2395
0!
b11101101 -
#2400
1!
#2401
b1101 %
17
#2405
0!
b11101110 -
#2410
1!
#2411
b1110 %
07
16
#2415
0!
b11101111 -
#2420
1!
#2421
b1111 %
17
#2425
0!
b11110000 -
#2430
1!
#2431
b1110 '
b0 %
b1111 $
13
07
06
05
04
b1111 ;
1?
b1110 @
b1110 8
b1110 &
#2435
0!
b11110001 -
#2440
1!
#2441
b1 %
17
#2445
0!
b11110010 -
#2450
1!
#2451
b10 %
07
16
#2455
0!
b11110011 -
#2460
1!
#2461
b11 %
17
#2465
0!
b11110100 -
#2470
1!
#2471
b100 %
07
06
15
#2475
0!
b11110101 -
#2480
1!
#2481
b101 %
17
#2485
0!
b11110110 -
#2490
1!
#2491
b110 %
07
16
#2495
0!
b11110111 -
#2500
1!
#2501
b111 %
17
#2505
0!
b11111000 -
#2510
1!
#2511
b1000 %
07
06
05
14
#2515
0!
b11111001 -
#2520
1!
#2521
b1001 %
17
#2525
0!
b11111010 -
#2530
1!
#2531
b1010 %
07
16
#2535
0!
b11111011 -
#2540
1!
#2541
b1011 %
17
#2545
0!
b11111100 -
#2550
1!
#2551
b1100 %
07
06
15
#2555
0!
b11111101 -
#2560
1!
#2561
b1101 %
17
#2565
0!
b11111110 -
#2570
1!
#2571
b1110 %
07
16
#2575
0!
b11111111 -
#2580
1!
#2581
b1111 %
17
#2585
0!
b100000000 -
#2590
1!
#2591
0,
1*
b1000000 '
0#
b0 %
b0 $
0/
03
02
01
00
07
06
05
04
b0 ;
19
0:
0+
1)
0?
0>
0=
0<
b1000000 @
b1000000 8
b1000000 &
#2595
0!
b100000001 -
#2600
1!
#2601
b1111001 '
b1 %
17
b1 ;
1?
b1111001 @
b1111001 8
b1111001 &
#2605
0!
b100000010 -
#2610
1!
#2611
b100100 '
b10 %
07
16
b10 ;
0?
1>
b100100 @
b100100 8
b100100 &
#2615
0!
b100000011 -
#2620
1!
#2621
b110000 '
b11 %
17
b11 ;
1?
b110000 @
b110000 8
b110000 &
#2625
0!
b100000100 -
#2630
1!
#2631
b11001 '
b100 %
07
06
15
b100 ;
0?
0>
1=
b11001 @
b11001 8
b11001 &
#2635
0!
b100000101 -
#2640
1!
#2641
b10010 '
b101 %
17
b101 ;
1?
b10010 @
b10010 8
b10010 &
#2645
0!
b100000110 -
#2650
1!
#2651
b10 '
b110 %
07
16
b110 ;
0?
1>
b10 @
b10 8
b10 &
#2655
0!
b100000111 -
#2660
1!
#2661
b1111000 '
b111 %
17
b111 ;
1?
b1111000 @
b1111000 8
b1111000 &
#2665
0!
b100001000 -
#2670
1!
#2671
b0 '
b1000 %
07
06
05
14
b1000 ;
0?
0>
0=
1<
b0 @
b0 8
b0 &
#2675
0!
b100001001 -
#2680
1!
#2681
b10000 '
b1001 %
17
b1001 ;
1?
b10000 @
b10000 8
b10000 &
#2685
0!
b100001010 -
#2690
1!
#2691
b1000 '
b1010 %
07
16
b1010 ;
0?
1>
b1000 @
b1000 8
b1000 &
#2695
0!
b100001011 -
#2700
1!
#2701
b11 '
b1011 %
17
b1011 ;
1?
b11 @
b11 8
b11 &
#2705
0!
b100001100 -
#2710
1!
#2711
b1000110 '
b1100 %
07
06
15
b1100 ;
0?
0>
1=
b1000110 @
b1000110 8
b1000110 &
#2715
0!
b100001101 -
#2720
1!
#2721
b100001 '
b1101 %
17
b1101 ;
1?
b100001 @
b100001 8
b100001 &
#2725
0!
b100001110 -
#2730
1!
#2731
b110 '
b1110 %
07
16
b1110 ;
0?
1>
b110 @
b110 8
b110 &
#2735
0!
b100001111 -
#2740
1!
#2741
b1110 '
b1111 %
17
b1111 ;
1?
b1110 @
b1110 8
b1110 &
#2745
0!
b100010000 -
#2750
1!
#2751
b1000000 '
b0 %
b1 $
13
07
06
05
04
b0 ;
0?
0>
0=
0<
b1000000 @
b1000000 8
b1000000 &
#2755
0!
b100010001 -
#2760
1!
#2761
b1111001 '
b1 %
17
b1 ;
1?
b1111001 @
b1111001 8
b1111001 &
#2765
0!
b100010010 -
#2770
1!
#2771
b100100 '
b10 %
07
16
b10 ;
0?
1>
b100100 @
b100100 8
b100100 &
#2775
0!
b100010011 -
#2780
1!
#2781
b110000 '
b11 %
17
b11 ;
1?
b110000 @
b110000 8
b110000 &
#2785
0!
b100010100 -
#2790
1!
#2791
b11001 '
b100 %
07
06
15
b100 ;
0?
0>
1=
b11001 @
b11001 8
b11001 &
#2795
0!
b100010101 -
#2800
1!
#2801
b10010 '
b101 %
17
b101 ;
1?
b10010 @
b10010 8
b10010 &
#2805
0!
b100010110 -
#2810
1!
#2811
b10 '
b110 %
07
16
b110 ;
0?
1>
b10 @
b10 8
b10 &
#2815
0!
b100010111 -
#2820
1!
#2821
b1111000 '
b111 %
17
b111 ;
1?
b1111000 @
b1111000 8
b1111000 &
#2825
0!
b100011000 -
#2830
1!
#2831
b0 '
b1000 %
07
06
05
14
b1000 ;
0?
0>
0=
1<
b0 @
b0 8
b0 &
#2835
0!
b100011001 -
#2840
1!
#2841
b10000 '
b1001 %
17
b1001 ;
1?
b10000 @
b10000 8
b10000 &
#2845
0!
b100011010 -
#2850
1!
#2851
b1000 '
b1010 %
07
16
b1010 ;
0?
1>
b1000 @
b1000 8
b1000 &
#2855
0!
b100011011 -
#2860
1!
#2861
b11 '
b1011 %
17
b1011 ;
1?
b11 @
b11 8
b11 &
#2865
0!
b100011100 -
#2870
1!
